MANIFEST.in
README.md
setup.py
brewblox_history/__init__.py
brewblox_history/__main__.py
brewblox_history/influx.py
brewblox_history.egg-info/PKG-INFO
brewblox_history.egg-info/SOURCES.txt
brewblox_history.egg-info/dependency_links.txt
brewblox_history.egg-info/requires.txt
brewblox_history.egg-info/top_level.txt
test/test_influx.py
test/test_main.py