Metadata-Version: 1.2
Name: brewblox-history
Version: 0.4.2
Summary: UNKNOWN
Home-page: https://github.com/BrewBlox/brewblox-history
Author: BrewPi
Author-email: development@brewpi.com
License: UNKNOWN
Keywords: brewing brewpi brewblox embedded plugin service
Platform: UNKNOWN
Classifier: Development Status :: 3 - Alpha
Classifier: License :: OSI Approved :: GNU General Public License (GPL)
Classifier: Programming Language :: Python :: 3.6
Classifier: Intended Audience :: End Users/Desktop
Classifier: Topic :: System :: Hardware
Requires-Python: >=3.6
